barak_the_king/__init__.py
barak_the_king-0.1.0.dist-info/METADATA
barak_the_king-0.1.0.dist-info/WHEEL
barak_the_king-0.1.0.dist-info/RECORD
