Metadata-Version: 2.1
Name: barak-the-king
Version: 0.1.0
Summary: 
Author: barak diker
Author-email: barakdiker@gmail.com
Requires-Python: >=3.11,<4.0
Classifier: Programming Language :: Python :: 3
Classifier: Programming Language :: Python :: 3.11
Classifier: Programming Language :: Python :: 3.12
Requires-Dist: pendulum (>=3.0.0,<4.0.0)
Requires-Dist: torch (>=2.1.2,<3.0.0)
